keys_management/__init__.py
keys_management/consts.py
keys_management/dependecies.py
keys_management/errors.py
keys_management/key_changed_utils.py
keys_management/key_definitions.py
keys_management/keys_management.py
keys_management/log_messages_consts.py
keys_management/on_change_key_definition.py
keys_management/concurrency/__init__.py
keys_management/secret_key/__init__.py
keys_management/secret_key/consts.py
keys_management/secret_key/errors.py
keys_management/secret_key/key_definition.py
keys_management/secret_key/key_state.py
keys_management/secret_key/log_messages_consts.py
keys_management/secret_key/secret_key.py
keys_management/secret_key/secret_key_use_case.py
keys_management/secret_key/types.py
keys_management-0.1.5.dist-info/LICENSE.txt
keys_management-0.1.5.dist-info/METADATA
keys_management-0.1.5.dist-info/WHEEL
keys_management-0.1.5.dist-info/top_level.txt
keys_management-0.1.5.dist-info/RECORD
