Metadata-Version: 2.1
Name: keys-management
Version: 0.1.5
Summary: An assistant Tool for manage application secret keys and rotations
Home-page: https://github.com/nielsen-oss/keys-management
Author: Ofek Israel
Author-email: ofek.israel@nielsen.com
License: UNKNOWN
Project-URL: Bug Tracker, https://github.com/nielsen-oss/keys-management/issues
Platform: UNKNOWN
Classifier: Programming Language :: Python :: 3
Classifier: Operating System :: OS Independent
Requires-Python: >=3.7
License-File: LICENSE.txt
